{
  "required": true,
  "package": "net.pm.stitched.mixin",
  "compatibilityLevel": "JAVA_17",
  "mixins": [
    "AbstractBlockMixin",
    "BlockBreakingMixin",
    "BlockMixin",
    "BlocksMixin",
    "BundleContentMixin",
    "CaveVineBodyBlockMixin",
    "EchoShardMixin",
    "EndermanMixin",
    "EntityMixin",
    "FarmlandMixin",
    "FireChargeMixin",
    "GrateBlockMixin",
    "HuskMixin",
    "IceMixin",
    "ItemFireproofMixin",
    "ItemImmuneExplosionMixin",
    "FoodComponentsMixin",
    "ItemUseMixin",
    "SnowMixin",
    "SweetBerryBushMixin"
  ],
  "injectors": {
    "defaultRequire": 1
	}
}